plimai/__init__.py
plimai/example.py
plimai/model_zoo.py
plimai/agents/__init__.py
plimai/callbacks/__init__.py
plimai/callbacks/base.py
plimai/callbacks/early_stopping.py
plimai/callbacks/logging.py
plimai/callbacks/registry.py
plimai/cli/__init__.py
plimai/cli/finetune.py
plimai/cli/train.py
plimai/components/__init__.py
plimai/components/attention.py
plimai/components/mlp.py
plimai/components/patch_embedding.py
plimai/config/__init__.py
plimai/data/__init__.py
plimai/data/datasets.py
plimai/filesystem/__init__.py
plimai/llm/__init__.py
plimai/memory/__init__.py
plimai/models/__init__.py
plimai/models/lora.py
plimai/models/vision_transformer.py
plimai/sync/__init__.py
plimai/telemetry/__init__.py
plimai/training/__init__.py
plimai/training/trainer.py
plimai/utils/__init__.py
plimai/utils/config.py
plimai/utils/cuda.py
plimai/utils/data.py
plimai/utils/device.py
plimai-0.1.9.dist-info/METADATA
plimai-0.1.9.dist-info/WHEEL
plimai-0.1.9.dist-info/entry_points.txt
plimai-0.1.9.dist-info/licenses/LICENSE
plimai-0.1.9.dist-info/RECORD
