Metadata-Version: 2.4
Name: plimai
Version: 0.1.9
Summary: Vision LLMs with LoRA fine-tuning.
Project-URL: Documentation, https://github.com/plimai/plim/tree/main/docs
Project-URL: Download, https://pypi.org/project/plimai/#files
Project-URL: Homepage, https://github.com/plimai/plim
Project-URL: Release Notes, https://github.com/plimai/plim/releases
Project-URL: Source, https://github.com/plimai/plim
Project-URL: Tracker, https://github.com/plimai/plim/issues
Project-URL: Funding, https://github.com/sponsors/plimai
Author-email: Plim <priteshraj41@gmail.com>
License-Expression: MIT
License-File: LICENSE
Classifier: License :: OSI Approved :: MIT License
Classifier: Operating System :: OS Independent
Classifier: Programming Language :: Python :: 3
Requires-Python: >=3.8
Requires-Dist: toml
Requires-Dist: torch
Requires-Dist: torchvision
